sc_orchestrator/cli.py
sc_orchestrator/core.py
sc_orchestrator/plugin_loader.py
sc_orchestrator/utils.py
sc_orchestrator/agents/backup_monitor.py
sc_orchestrator/agents/project_manager.py
sc_orchestrator/agents/quoting.py
sc_orchestrator/agents/vciso.py
sc_orchestrator/connectors/galactic.py
sc_orchestrator/connectors/superops.py
sc_orchestrator/connectors/veeam.py
sc_orchestrator-0.2.19.dist-info/METADATA
sc_orchestrator-0.2.19.dist-info/WHEEL
sc_orchestrator-0.2.19.dist-info/entry_points.txt
sc_orchestrator-0.2.19.dist-info/top_level.txt
sc_orchestrator-0.2.19.dist-info/RECORD
