Metadata-Version: 2.4
Name: sc-orchestrator
Version: 0.2.19
Summary: Szymanski Consulting – Orchestrator for PM/vCISO/Quoting
Requires-Python: >=3.11
Requires-Dist: PyYAML>=6.0.2
Requires-Dist: pytz>=2024.1
Requires-Dist: requests>=2.32.3
